plot.py
scientific_data_plotter-1.0.1.dist-info/METADATA
scientific_data_plotter-1.0.1.dist-info/WHEEL
scientific_data_plotter-1.0.1.dist-info/top_level.txt
scientific_data_plotter-1.0.1.dist-info/RECORD
