Metadata-Version: 2.1
Name: scientific-data-plotter
Version: 1.0.1
Summary: Scientific data Plotter Python package
Author: Affan Iqbal
License: MIT
Requires-Dist: tk
Requires-Dist: openpyxl
Requires-Dist: pandas
Requires-Dist: matplotlib
